README.txt
setup.py
typechecking.py
TypeChecking.egg-info/PKG-INFO
TypeChecking.egg-info/SOURCES.txt
TypeChecking.egg-info/dependency_links.txt
TypeChecking.egg-info/top_level.txt